pybloxy/__init__.py
pybloxy/classes/assets.py
pybloxy/classes/friends.py
pybloxy/classes/groups.py
pybloxy/classes/http.py
pybloxy/classes/user.py
pybloxy/classes/util.py
pybloxy-0.2.1.dist-info/LICENSE.txt
pybloxy-0.2.1.dist-info/WHEEL
pybloxy-0.2.1.dist-info/METADATA
pybloxy-0.2.1.dist-info/RECORD
