Metadata-Version: 2.1
Name: pybloxy
Version: 0.2.1
Summary: A simplistic Roblox API wrapper written in Python.
Author: R0bl0x10501050
Author-email: r0bl0x10501050@gmail.com
Requires-Python: >=3.8,<4.0
Classifier: Programming Language :: Python :: 3
Classifier: Programming Language :: Python :: 3.8
Requires-Dist: requests (>=2.2,<3.0)
